{
  "url": "https://www.allocine.fr/series/ficheserie_gen_cserie=22125.html",
  "original_title": "Demain nous appartient",
  "date": "Depuis 2017",
  "running_time": "30min",
  "genres": [
    "Drame",
    "Thriller"
  ],
  "created_by": [
    "Frédéric Chansel",
    "Laure de Colbert",
    "Nicolas Durand-Zouky"
  ],
  "spectators_mean_rating": "2,1",
  "press_mean_rating": "3,2",
  "actors": [
    "Ingrid Chauvin",
    "Alexandre Brasseur",
    "Lorie Pester",
    "Maud Baecker"
  ],
  "country_of_origin": "France",
  "nb_seasons": 4,
  "nb_episodes": 927,
  "synopsis": "Le quotidien à Sète, dans le Sud de la France, des familles Delcourt, Vallorta, Lazzari, Beddiar, et Moreno, entre histoires d'amour, trahisons, scandales, affaires policières, traques de tueurs en série, et amitiés mises à rude épreuve.",
  "collect_date": "2021_04_22"
}