{
  "url": "https://www.allocine.fr/series/ficheserie_gen_cserie=22123.html",
  "original_title": "9-1-1",
  "date": "Depuis 2018",
  "running_time": "42min",
  "genres": [
    "Drame",
    "Action"
  ],
  "created_by": [
    "Ryan Murphy",
    "Brad Falchuk",
    "Tim Minear"
  ],
  "spectators_mean_rating": "4,0",
  "press_mean_rating": "3,0",
  "actors": [
    "Angela Bassett",
    "Peter Krause",
    "Jennifer Love Hewitt",
    "Oliver Stark"
  ],
  "country_of_origin": "U.S.A.",
  "nb_seasons": 4,
  "nb_episodes": 59,
  "synopsis": "Du service d'appels d'urgences 911 aux pompiers, secouristes ou policiers, tous ces intervenants sont constamment sous pression, confrontés quotidiennement à des situations stupéfiantes, effrayantes, et parfois même choquantes. S'ils ont pour mission de voler au secours des personnes en danger, ces héros de l'ombre doivent aussi trouver le temps de résoudre les problèmes de leurs propres vies...",
  "collect_date": "2021_04_22"
}