{
  "url": "https://www.allocine.fr/series/ficheserie_gen_cserie=23929.html",
  "original_title": "White Lines",
  "date": "2020",
  "running_time": "55min",
  "genres": [
    "Drame",
    "Policier",
    "Thriller"
  ],
  "created_by": [
    "Álex Pina"
  ],
  "spectators_mean_rating": "3,4",
  "press_mean_rating": "2,8",
  "actors": [
    "Laura Haddock",
    "Tom Rhys Harries",
    "Daniel Mays",
    "Nuno Lopes"
  ],
  "country_of_origin": "U.S.A.",
  "nb_seasons": 1,
  "nb_episodes": 10,
  "synopsis": "Suite à la découverte du corps d'Axel Collins, un jeune DJ anglais disparu 20 ans plus tôt, dans le désert espagnol, sa soeur, Zoe, se rend alors à Ibiza, là où Alex a été vu pour la dernière fois, afin de découvrir ce qui s’est réellement passé. Son enquête au sein de ce haut lieu de la fête la forcera à affronter les côtés les plus dangereux et les plus déréglés de l'île, ainsi que ses propres démons.",
  "collect_date": "2021_04_22"
}