[
    {
        "serie_name": "Homeland",
        "serie_url": "https://www.allocine.fr/series/ficheserie_gen_cserie=9285.html",
        "series_reviews_page": "https://www.allocine.fr/series/ficheserie-9285/critiques/"
    },
    {
        "serie_name": "Into the Badlands",
        "serie_url": "https://www.allocine.fr/series/ficheserie_gen_cserie=17761.html",
        "series_reviews_page": "https://www.allocine.fr/series/ficheserie-17761/critiques/"
    },
    {
        "serie_name": "This is Us",
        "serie_url": "https://www.allocine.fr/series/ficheserie_gen_cserie=19992.html",
        "series_reviews_page": "https://www.allocine.fr/series/ficheserie-19992/critiques/"
    },
    {
        "serie_name": "Breaking Bad",
        "serie_url": "https://www.allocine.fr/series/ficheserie_gen_cserie=3517.html",
        "series_reviews_page": "https://www.allocine.fr/series/ficheserie-3517/critiques/"
    },
    {
        "serie_name": "Salamandre",
        "serie_url": "https://www.allocine.fr/series/ficheserie_gen_cserie=12222.html",
        "series_reviews_page": "https://www.allocine.fr/series/ficheserie-12222/critiques/"
    },
    {
        "serie_name": "The One",
        "serie_url": "https://www.allocine.fr/series/ficheserie_gen_cserie=24465.html",
        "series_reviews_page": "https://www.allocine.fr/series/ficheserie-24465/critiques/"
    },
    {
        "serie_name": "Élite",
        "serie_url": "https://www.allocine.fr/series/ficheserie_gen_cserie=22373.html",
        "series_reviews_page": "https://www.allocine.fr/series/ficheserie-22373/critiques/"
    },
    {
        "serie_name": "Shameless (US)",
        "serie_url": "https://www.allocine.fr/series/ficheserie_gen_cserie=7634.html",
        "series_reviews_page": "https://www.allocine.fr/series/ficheserie-7634/critiques/"
    },
    {
        "serie_name": "Stranger Things",
        "serie_url": "https://www.allocine.fr/series/ficheserie_gen_cserie=19156.html",
        "series_reviews_page": "https://www.allocine.fr/series/ficheserie-19156/critiques/"
    },
    {
        "serie_name": "Le jeu de la dame",
        "serie_url": "https://www.allocine.fr/series/ficheserie_gen_cserie=24971.html",
        "series_reviews_page": "https://www.allocine.fr/series/ficheserie-24971/critiques/"
    },
    {
        "serie_name": "Validé",
        "serie_url": "https://www.allocine.fr/series/ficheserie_gen_cserie=24293.html",
        "series_reviews_page": "https://www.allocine.fr/series/ficheserie-24293/critiques/"
    },
    {
        "serie_name": "Made for Love",
        "serie_url": "https://www.allocine.fr/series/ficheserie_gen_cserie=25284.html",
        "series_reviews_page": "https://www.allocine.fr/series/ficheserie-25284/critiques/"
    },
    {
        "serie_name": "La Chronique des Bridgerton",
        "serie_url": "https://www.allocine.fr/series/ficheserie_gen_cserie=23886.html",
        "series_reviews_page": "https://www.allocine.fr/series/ficheserie-23886/critiques/"
    },
    {
        "serie_name": "Lucifer",
        "serie_url": "https://www.allocine.fr/series/ficheserie_gen_cserie=18145.html",
        "series_reviews_page": "https://www.allocine.fr/series/ficheserie-18145/critiques/"
    }
]